captchakiller/__init__.py
captchakiller/ck.py
captchakiller/utils.py
captchakiller_python-0.0.8.dist-info/LICENSE
captchakiller_python-0.0.8.dist-info/METADATA
captchakiller_python-0.0.8.dist-info/WHEEL
captchakiller_python-0.0.8.dist-info/top_level.txt
captchakiller_python-0.0.8.dist-info/RECORD
