Metadata-Version: 2.1
Name: captchakiller-python
Version: 0.0.8
Summary: CaptchaKiller Python API Client Library, for solving captchas. Fast Recaptcha, funcaptcha, mtcaptcha Captcha Solver
Home-page: https://github.com/captchakillernet/captchakiller-python
Author: captchakiller
Author-email: support@captchakiller.net
Project-URL: Homepage, https://captchakiller.net
Project-URL: Documentation, https://captchakiller.gitbook.io
Classifier: Programming Language :: Python :: 3
Classifier: License :: OSI Approved :: MIT License
Classifier: Operating System :: OS Independent
Requires-Python: >=3.6
License-File: LICENSE
Requires-Dist: requests
